pyglottography/__init__.py
pyglottography/dataset.py
pyglottography/scaffold.py
pyglottography/util.py
pyglottography/commands/__init__.py
pyglottography/commands/map.html.mako
pyglottography/commands/release.py
pyglottography/commands/showmap.py
pyglottography/glottography_template/CONTRIBUTORS.md
pyglottography/glottography_template/RELEASING.md_tmpl
pyglottography/glottography_template/cldfbench_+id+.py_tmpl
pyglottography/glottography_template/setup.cfg
pyglottography/glottography_template/setup.py_tmpl
pyglottography/glottography_template/test.py
pyglottography/glottography_template/.github/workflows/cldf-validation.yml
pyglottography/glottography_template/etc/README.md
pyglottography-1.1.0.dist-info/LICENSE
pyglottography-1.1.0.dist-info/METADATA
pyglottography-1.1.0.dist-info/WHEEL
pyglottography-1.1.0.dist-info/entry_points.txt
pyglottography-1.1.0.dist-info/top_level.txt
pyglottography-1.1.0.dist-info/RECORD
